{"notebooks":{"transit.jl":{"id":"transit.jl","hash":"SHjdqexC8RINuTjR26O71Y-odnhZkXonwA-ZHF-TrYU","html_path":"transit.html","statefile_path":"transit.plutostate","notebookfile_path":"transit.jl","current_hash":"SHjdqexC8RINuTjR26O71Y-odnhZkXonwA-ZHF-TrYU","desired_hash":"SHjdqexC8RINuTjR26O71Y-odnhZkXonwA-ZHF-TrYU","frontmatter":{"author":[{"name":"Jeanne Laflamme"}],"image":"https://cdn-icons-png.flaticon.com/512/4565/4565023.png","language":"fr-CA","title":"Proposition de modification au TCJC","date":"2026-03-11"}}},"pluto_version":"0.20.24","julia_version":"1.12.5","format_version":"1","content_git_hash":"805d160","title":null,"description":null,"collections":null,"binder_url":"https://mybinder.org/v2/gh/fonsp/pluto-on-binder/v0.20.24","slider_server_url":null}